[
  {
    "name": "Validate_ImportUndertakingCCN", 
    "endpoint": "importUndertakingCCN", 
    "failOnError": null, 
    "failOnBusy": null, 
    "parameters": [
      {
        "name": "CCN", 
        "path": "value"
      },
      {
        "name": "valueDate", 
        "path": "transaction::ValueDate"
      }
    ]
  },
  {
    "name": "Retrieve_ReversalPossibleTrnData", 
    "endpoint": "reversalOriginalTRNs", 
    "failOnError": null, 
    "failOnBusy": null, 
    "parameters": [
      {
        "name": "trnReference", 
        "path": "value"
      },
      {
        "name": "flow", 
        "path": "transaction::Flow"
      }
    ]
  },
  {
    "name": "Validate_ValidCCN", 
    "endpoint": "validCCN", 
    "failOnError": null, 
    "failOnBusy": null, 
    "parameters": [
      {
        "name": "CCN", 
        "path": "value"
      },
      {
        "name": "valueDate", 
        "path": "transaction::ValueDate"
      }
    ]
  },
  {
    "name": "Verify_ARM", 
    "endpoint": "verifyARM", 
    "failOnError": "true", 
    "failOnBusy": "true", 
    "parameters": [
      {
        "name": "FieldValue", 
        "path": "value"
      },
      {
        "name": "TrnRef", 
        "path": "transaction::TrnReference"
      },
      {
        "name": "Seq", 
        "path": "money::SequenceNumber"
      },
      {
        "name": "Flow", 
        "path": "transaction::Flow"
      },
      {
        "name": "ValueDate", 
        "path": "transaction::ValueDate"
      },
      {
        "name": "FlowCurrency", 
        "path": "transaction::FlowCurrency"
      },
      {
        "name": "TotalFlowAmount", 
        "path": "transaction::TotalForeignValue"
      },
      {
        "name": "FlowAmount", 
        "path": "money::ForeignValue"
      },
      {
        "name": "RegulatorAuth", 
        "path": "money::RegulatorAuth.CBAuthAppNumber"
      },
      {
        "name": "RegulatorAuthDate", 
        "path": "money::RegulatorAuth.CBAuthDate"
      },
      {
        "name": "InternalAuth", 
        "path": "money::RegulatorAuth.REInternalAuthNumber"
      },
      {
        "name": "InternalAuthDate", 
        "path": "money::RegulatorAuth.REInternalAuthNumberDate"
      }
    ]
  },
  {
    "name": "Validate_IndividualSDA", 
    "endpoint": "withinSDALimit", 
    "failOnError": null, 
    "failOnBusy": null, 
    "parameters": [
      {
        "name": "idNumber", 
        "path": "value"
      },
      {
        "name": "trnRef", 
        "path": "transaction::TrnReference"
      },
      {
        "name": "valueDate", 
        "path": "transaction::ValueDate"
      },
      {
        "name": "localAmountForIDNumber", 
        "path": "function::localAmountForIDNumber"
      }
    ]
  },
  {
    "name": "Retrieve_ReversalOriginalData", 
    "endpoint": "reversalOriginalData", 
    "failOnError": null, 
    "failOnBusy": null, 
    "parameters": [
      {
        "name": "trnReference", 
        "path": "value"
      },
      {
        "name": "flow", 
        "path": "transaction::Flow"
      }
    ]
  },
  {
    "name": "Validate_ReplacementTrnReference", 
    "endpoint": "replacementTrnReference", 
    "failOnError": null, 
    "failOnBusy": null, 
    "parameters": [
      {
        "name": "replacementTrnReference", 
        "path": "ReplacementOriginalReference"
      }
    ]
  },
  {
    "name": "Validate_LoanRef", 
    "endpoint": "loanRef", 
    "failOnError": "true", 
    "failOnBusy": "true", 
    "parameters": [
      {
        "name": "loanReference", 
        "path": "value"
      },
      {
        "name": "loanRef", 
        "path": "money::LoanRefNumber"
      },
      {
        "name": "valueDate", 
        "path": "transaction::ValueDate"
      },
      {
        "name": "REAccountNumber", 
        "path": "transaction::Resident.Entity.AccountNumber"
      },
      {
        "name": "REAccountIdentifier", 
        "path": "transaction::Resident.Entity.AccountIdentifier"
      },
      {
        "name": "RIAccountNumber", 
        "path": "transaction::Resident.Individual.AccountNumber"
      },
      {
        "name": "RIAccountIdentifier", 
        "path": "transaction::Resident.Individual.AccountIdentifier"
      }
    ]
  },
  {
    "name": "Validate_ReversalTrnRef", 
    "endpoint": "reversalTrnRef", 
    "failOnError": "true", 
    "failOnBusy": "true", 
    "parameters": [
      {
        "name": "reversalTrnRefVal", 
        "path": "value"
      },
      {
        "name": "reversalTrnRef", 
        "path": "money::ReversalTrnRefNumber"
      },
      {
        "name": "trnReference", 
        "path": "transaction::TrnReference"
      },
      {
        "name": "flowCurrency", 
        "path": "transaction::FlowCurrency"
      },
      {
        "name": "flow", 
        "path": "transaction::Flow"
      },
      {
        "name": "reversalTrnSeq", 
        "path": "money::ReversalTrnSeqNumber"
      },
      {
        "name": "sequence", 
        "path": "money::ReversalTrnSeqNumber"
      },
      {
        "name": "foreignValue", 
        "path": "money::ForeignValue"
      },
      {
        "name": "category", 
        "path": "money::CategoryCode"
      }
    ]
  },
  {
    "name": "Validate_IndividualFIA", 
    "endpoint": "withinFIALimit", 
    "failOnError": null, 
    "failOnBusy": null, 
    "parameters": [
      {
        "name": "idNumber", 
        "path": "value"
      },
      {
        "name": "trnRef", 
        "path": "transaction::TrnReference"
      },
      {
        "name": "valueDate", 
        "path": "transaction::ValueDate"
      },
      {
        "name": "localAmountForIDNumberFIA", 
        "path": "function::localAmountForIDNumberFIA"
      }
    ]
  },
  {
    "name": "Validate_ValidCCNinUCR", 
    "endpoint": "validCCNinUCR", 
    "failOnError": null, 
    "failOnBusy": null, 
    "parameters": [
      {
        "name": "UCR", 
        "path": "value"
      },
      {
        "name": "valueDate", 
        "path": "transaction::ValueDate"
      }
    ]
  },
  {
    "name": "Validate_IVS", 
    "endpoint": "validateIVS", 
    "failOnError": null, 
    "failOnBusy": null, 
    "parameters": [
      {
        "name": "FieldValue", 
        "path": "value"
      },
      {
        "name": "TrnRef", 
        "path": "transaction::TrnReference"
      },
      {
        "name": "Seq", 
        "path": "money::SequenceNumber"
      },
      {
        "name": "ThirdPartyCCN", 
        "path": "money::ThirdParty.CustomsClientNumber"
      },
      {
        "name": "ResidentInvCCN", 
        "path": "transaction::Resident.Individual.CustomsClientNumber"
      },
      {
        "name": "ResidentEntityCCN", 
        "path": "transaction::Resident.Entity.CustomsClientNumber"
      },
      {
        "name": "TDN", 
        "path": "TransportDocumentNumber"
      },
      {
        "name": "MRN", 
        "path": "ImportControlNumber"
      }
    ]
  }
]